cdis/__init__.py
cdis/_bytecode.py
cdis/_compiler.py
cdis/_type_analysis.py
cdis/_vm.py
cdis-0.0.0a0.dist-info/METADATA
cdis-0.0.0a0.dist-info/WHEEL
cdis-0.0.0a0.dist-info/licenses/LICENSE.txt
cdis-0.0.0a0.dist-info/RECORD
