Metadata-Version: 2.4
Name: cdis
Version: 0.0.0a0
Project-URL: Homepage, https://github.com/cdis-vm/cdis/tree/main
Project-URL: Repository, https://github.com/cdis-vm/cdis.git
Project-URL: Issues, https://github.com/cdis-vm/cdis/issues
License-Expression: Apache-2.0
License-File: LICENSE.txt
Keywords: cdis,code analysis,code generation,dis,disassembly
Classifier: Development Status :: 2 - Pre-Alpha
Classifier: Intended Audience :: Developers
Classifier: Programming Language :: Python :: 3.10
Classifier: Programming Language :: Python :: 3.11
Classifier: Programming Language :: Python :: 3.12
Classifier: Programming Language :: Python :: 3.13
Classifier: Topic :: Software Development :: Code Generators
Classifier: Topic :: Software Development :: Compilers
Classifier: Topic :: Software Development :: Debuggers
Classifier: Topic :: Software Development :: Disassemblers
Requires-Python: >=3.10
